{
    "schemes": [
        {
            "name": "Ubuntu",
            "foreground": "#eeeeec",
            "background": "#300a24",
            "black": "#2e3436",
            "red": "#cc0000",
            "green": "#4e9a06",
            "yellow": "#c4a000",
            "blue": "#3465a4",
            "purple": "#75507b",
            "cyan": "#06989a",
            "white": "#d3d7cf",
            "brightBlack": "#555753",
            "brightRed": "#ef2929",
            "brightGreen": "#8ae234",
            "brightYellow": "#fce94f",
            "brightBlue": "#729fcf",
            "brightPurple": "#ad7fa8",
            "brightCyan": "#34e2e2",
            "brightWhite": "#eeeeec"
          },
          {
            "name": "Monokai Soda",
            "black": "#1a1a1a",
            "red": "#f4005f",
            "green": "#98e024",
            "yellow": "#fa8419",
            "blue": "#9d65ff",
            "purple": "#f4005f",
            "cyan": "#58d1eb",
            "white": "#c4c5b5",
            "brightBlack": "#625e4c",
            "brightRed": "#f4005f",
            "brightGreen": "#98e024",
            "brightYellow": "#e0d561",
            "brightBlue": "#9d65ff",
            "brightPurple": "#f4005f",
            "brightCyan": "#58d1eb",
            "brightWhite": "#f6f6ef",
            "background": "#1a1a1a",
            "foreground": "#c4c5b5"
          }
    ]
}